furhat_remote_api/__init__.py
swagger_client/__init__.py
swagger_client/api_client.py
swagger_client/configuration.py
swagger_client/rest.py
swagger_client/api/__init__.py
swagger_client/api/furhat_api.py
swagger_client/models/__init__.py
swagger_client/models/basic_param.py
swagger_client/models/frame.py
swagger_client/models/gesture.py
swagger_client/models/gesture_definition.py
swagger_client/models/location.py
swagger_client/models/rotation.py
swagger_client/models/status.py
swagger_client/models/user.py
swagger_client/models/voice.py
test/__init__.py
test/test_basic_param.py
test/test_frame.py
test/test_furhat_api.py
test/test_gesture.py
test/test_gesture_definition.py
test/test_location.py
test/test_rotation.py
test/test_status.py
test/test_user.py
test/test_voice.py
furhat_remote_api-1.0.2.dist-info/LICENSE.md
furhat_remote_api-1.0.2.dist-info/METADATA
furhat_remote_api-1.0.2.dist-info/WHEEL
furhat_remote_api-1.0.2.dist-info/top_level.txt
furhat_remote_api-1.0.2.dist-info/RECORD
