Metadata-Version: 2.1
Name: furhat-remote-api
Version: 1.0.2
Summary: Furhat Remote API
Home-page: UNKNOWN
Author-email: support@furhatrobotics.com
License: UNKNOWN
Keywords: Swagger,Furhat Remote API
Platform: UNKNOWN
License-File: LICENSE.md
